{"attributes": {"Name": "Value Network minimal", "edgeType": "undirected"}, "nodes": [{"id": 0, "position": {"x": 0.9999999882774899, "y": 1.3311835367777423e-08}, "attributes": {"Business Role": "Supplier", "Criminal Capital": 0.9, "Violence Capital": 0.5, "Financial Capital": 0.6}}, {"id": 1, "position": {"x": 0.9510565289413768, "y": 0.30901701178080193}, "attributes": {"Business Role": "Gatekeeper", "Criminal Capital": 0.9, "Violence Capital": 0.25, "Financial Capital": 0.5}}, {"id": 2, "position": {"x": 0.8090169934023742, "y": 0.587785249475372}, "attributes": {"Business Role": "Financer", "Criminal Capital": 0.8, "Violence Capital": 0.4, "Financial Capital": 0.9}}, {"id": 3, "position": {"x": 0.587785237752862, "y": 0.8090170051248842}, "attributes": {"Business Role": "Placer inland", "Criminal Capital": 0.5, "Violence Capital": 0.55, "Financial Capital": 0.1}}, {"id": 4, "position": {"x": 0.30901697025596997, "y": 0.9510565406638868}, "attributes": {"Business Role": "Transporter", "Criminal Capital": 0.1, "Violence Capital": 0.4, "Financial Capital": 0.5}}, {"id": 5, "position": {"x": -4.212206234360422e-08, "y": 1.0}, "attributes": {"Business Role": "Stasher", "Criminal Capital": 0.025, "Violence Capital": 0.55, "Financial Capital": 0.1}}, {"id": 6, "position": {"x": -0.3090170266819632, "y": 0.9510564810592429}, "attributes": {"Business Role": "Security guard", "Criminal Capital": 0.075, "Violence Capital": 0.85, "Financial Capital": 0.1}}, {"id": 7, "position": {"x": -0.5877852345742114, "y": 0.8090170051248842}, "attributes": {"Business Role": "Cutter", "Criminal Capital": 0.1, "Violence Capital": 0.1, "Financial Capital": 0.1}}, {"id": 8, "position": {"x": -0.8090169902237235, "y": 0.587785249475372}, "attributes": {"Business Role": "Retrievers broker", "Criminal Capital": 0.75, "Violence Capital": 0.5, "Financial Capital": 0.55}}, {"id": 9, "position": {"x": -0.9510564661580821, "y": 0.30901704158312393}, "attributes": {"Business Role": "Customs officer", "Criminal Capital": 0.65, "Violence Capital": 0.4, "Financial Capital": 0.1}}, {"id": 10, "position": {"x": -0.9999999850988393, "y": -7.411094004194081e-08}, "attributes": {"Business Role": "Retriever", "Criminal Capital": 0.1, "Violence Capital": 0.55, "Financial Capital": 0.1}}, {"id": 11, "position": {"x": -0.9510565257627261, "y": -0.3090169553548092}, "attributes": {"Business Role": "Frontman", "Criminal Capital": 0.1, "Violence Capital": 0.55, "Financial Capital": 0.1}}, {"id": 12, "position": {"x": -0.8090169306190795, "y": -0.5877852824563453}, "attributes": {"Business Role": "Dealer", "Criminal Capital": 0.45, "Violence Capital": 0.5, "Financial Capital": 0.55}}, {"id": 13, "position": {"x": -0.5877850557602794, "y": -0.8090170977105015}, "attributes": {"Business Role": "Driver", "Criminal Capital": 0.1, "Violence Capital": 0.1, "Financial Capital": 0.1}}, {"id": 14, "position": {"x": -0.3090171160889292, "y": -0.9510564544355722}, "attributes": {"Business Role": "Coordinator", "Criminal Capital": 0.95, "Violence Capital": 0.5, "Financial Capital": 0.65}}, {"id": 15, "position": {"x": 1.3514205841015913e-08, "y": -0.9999999733763293}, "attributes": {"Business Role": "Murder broker", "Criminal Capital": 0.3, "Violence Capital": 0.8, "Financial Capital": 0.3}}, {"id": 16, "position": {"x": 0.3090171192675799, "y": -0.9510564544355722}, "attributes": {"Business Role": "Assassin", "Criminal Capital": 0.3, "Violence Capital": 0.9, "Financial Capital": 0.3}}, {"id": 17, "position": {"x": 0.5877850589389301, "y": -0.8090170977105015}, "attributes": {"Business Role": "Organizer", "Criminal Capital": 0.95, "Violence Capital": 0.5, "Financial Capital": 0.65}}, {"id": 18, "position": {"x": 0.8090169337977302, "y": -0.5877852824563453}, "attributes": {"Business Role": "Kingpin", "Criminal Capital": 0.9, "Violence Capital": 0.5, "Financial Capital": 0.6}}, {"id": 19, "position": {"x": 0.9510565289413768, "y": -0.3090169255524872}, "attributes": {"Business Role": "Exporter", "Criminal Capital": 0.34, "Violence Capital": 0.5, "Financial Capital": 0.55}}], "edges": [{"source": "0", "target": "1", "attributes": {}}, {"source": "0", "target": "18", "attributes": {}}, {"source": "0", "target": "17", "attributes": {}}, {"source": "0", "target": "0", "attributes": {}}, {"source": "1", "target": "2", "attributes": {}}, {"source": "1", "target": "8", "attributes": {}}, {"source": "1", "target": "9", "attributes": {}}, {"source": "1", "target": "18", "attributes": {}}, {"source": "2", "target": "1", "attributes": {}}, {"source": "2", "target": "3", "attributes": {}}, {"source": "2", "target": "4", "attributes": {}}, {"source": "2", "target": "5", "attributes": {}}, {"source": "2", "target": "6", "attributes": {}}, {"source": "2", "target": "7", "attributes": {}}, {"source": "2", "target": "14", "attributes": {}}, {"source": "2", "target": "17", "attributes": {}}, {"source": "2", "target": "0", "attributes": {}}, {"source": "2", "target": "12", "attributes": {}}, {"source": "3", "target": "2", "attributes": {}}, {"source": "3", "target": "3", "attributes": {}}, {"source": "3", "target": "1", "attributes": {}}, {"source": "4", "target": "1", "attributes": {}}, {"source": "5", "target": "2", "attributes": {}}, {"source": "5", "target": "6", "attributes": {}}, {"source": "5", "target": "11", "attributes": {}}, {"source": "6", "target": "2", "attributes": {}}, {"source": "6", "target": "5", "attributes": {}}, {"source": "6", "target": "7", "attributes": {}}, {"source": "7", "target": "12", "attributes": {}}, {"source": "7", "target": "5", "attributes": {}}, {"source": "8", "target": "2", "attributes": {}}, {"source": "8", "target": "10", "attributes": {}}, {"source": "8", "target": "14", "attributes": {}}, {"source": "8", "target": "17", "attributes": {}}, {"source": "9", "target": "8", "attributes": {}}, {"source": "9", "target": "9", "attributes": {}}, {"source": "9", "target": "1", "attributes": {}}, {"source": "10", "target": "8", "attributes": {}}, {"source": "12", "target": "5", "attributes": {}}, {"source": "12", "target": "6", "attributes": {}}, {"source": "12", "target": "12", "attributes": {}}, {"source": "12", "target": "4", "attributes": {}}, {"source": "12", "target": "1", "attributes": {}}, {"source": "13", "target": "4", "attributes": {}}, {"source": "13", "target": "12", "attributes": {}}, {"source": "14", "target": "1", "attributes": {}}, {"source": "14", "target": "3", "attributes": {}}, {"source": "14", "target": "4", "attributes": {}}, {"source": "14", "target": "5", "attributes": {}}, {"source": "14", "target": "6", "attributes": {}}, {"source": "14", "target": "7", "attributes": {}}, {"source": "14", "target": "8", "attributes": {}}, {"source": "15", "target": "16", "attributes": {}}, {"source": "16", "target": "15", "attributes": {}}, {"source": "17", "target": "18", "attributes": {}}, {"source": "17", "target": "15", "attributes": {}}, {"source": "17", "target": "8", "attributes": {}}, {"source": "17", "target": "0", "attributes": {}}, {"source": "17", "target": "1", "attributes": {}}, {"source": "19", "target": "17", "attributes": {}}, {"source": "19", "target": "14", "attributes": {}}, {"source": "19", "target": "4", "attributes": {}}, {"source": "19", "target": "1", "attributes": {}}]}